imageconvert/__init__.py
imageconvert/imageconvert.py
imageconvert-0.3.2.dist-info/licenses/LICENSE
imageconvert-0.3.2.dist-info/METADATA
imageconvert-0.3.2.dist-info/WHEEL
imageconvert-0.3.2.dist-info/top_level.txt
imageconvert-0.3.2.dist-info/RECORD
