Metadata-Version: 2.4
Name: imageconvert
Version: 0.3.2
Summary: A Python library for converting between different image formats with metadata preservation
Author-email: mricardo <ricardo.lee.cm@gmail.com>
Maintainer-email: mricardo <ricardo.lee.cm@gmail.com>
License-Expression: MIT
Project-URL: Homepage, https://github.com/mricardo888/ImageConvert
Project-URL: Bug Tracker, https://github.com/mricardo888/ImageConvert/issues
Project-URL: GitHub Docs, https://github.com/mricardo888/ImageConvert#readme
Project-URL: Documentation, https://ricardos-projects.gitbook.io/imageconvert-docs
Keywords: image,conversion,metadata,exif,photos,avif,heif,heic,webp,jfif,pdf
Classifier: Development Status :: 5 - Production/Stable
Classifier: Programming Language :: Python :: 3.7
Classifier: Programming Language :: Python :: 3.8
Classifier: Programming Language :: Python :: 3.9
Classifier: Programming Language :: Python :: 3.10
Classifier: Programming Language :: Python :: 3.11
Classifier: Programming Language :: Python :: 3.12
Classifier: Programming Language :: Python :: 3.13
Classifier: Topic :: Multimedia :: Graphics :: Graphics Conversion
Classifier: Topic :: Multimedia :: Graphics :: Capture
Classifier: Topic :: Multimedia :: Graphics :: Viewers
Requires-Python: >=3.7
License-File: LICENSE
Requires-Dist: Pillow>=9.3.0
Requires-Dist: pillow-heif>=0.13.0
Requires-Dist: piexif>=1.1.3
Requires-Dist: svglib>=1.2.0
Requires-Dist: reportlab>=3.6.0
Requires-Dist: rawpy>=0.17.0
Requires-Dist: PyMuPDF>=1.21.0
Requires-Dist: win32-setctime>=1.1.0; platform_system == "Windows"
Dynamic: license-file
